neelanjanmannaqr.py
neelanjanmannaqr-3.dist-info/METADATA
neelanjanmannaqr-3.dist-info/WHEEL
neelanjanmannaqr-3.dist-info/top_level.txt
neelanjanmannaqr-3.dist-info/RECORD
