Metadata-Version: 2.1
Name: neelanjanmannaqr
Version: 3
Summary: encrypted messaging via qr
Author: Neelanjan Manna
Classifier: Programming Language :: Python :: 3
Classifier: License :: OSI Approved :: MIT License
Classifier: Operating System :: OS Independent
Requires-Python: >=3.6
Requires-Dist: pycryptodome
